example_package_irshad_calculator/add.cp312-win_amd64.pyd
example_package_irshad_calculator-0.2.dist-info/METADATA
example_package_irshad_calculator-0.2.dist-info/WHEEL
example_package_irshad_calculator-0.2.dist-info/top_level.txt
example_package_irshad_calculator-0.2.dist-info/RECORD
