Metadata-Version: 2.1
Name: example_package_irshad_calculator
Version: 0.2
Summary: Packaging concept
Home-page: 
Author: Irshad
Author-email: 
Classifier: Programming Language :: Python :: 3
Classifier: License :: OSI Approved :: MIT License
Classifier: Operating System :: OS Independent
Requires-Python: >=3.6
